{
    "records": {
        "2018": {
            "validhits": [
                {
                    "robot_agent": "Go-http-client/1.1",
                    "useragent": "Go-http-client/1.1",
                    "value": "20"
                }
            ]
        },
        "2019-01": {
            "validhits": [
                {
                    "robot_agent": "Go-http-client/1.1",
                    "useragent": "Go-http-client/1.1",
                    "value": "3"
                }
            ]
        },
        "2019-02": {
            "validhits": [
                {
                    "robot_agent": "Go-http-client/1.1",
                    "useragent": "Go-http-client/1.1",
                    "value": "2"
                }
            ]
        },
        "2019-03": {
            "validhits": [
                {
                    "robot_agent": "Go-http-client/1.1",
                    "useragent": "Go-http-client/1.1",
                    "value": "3"
                }
            ]
        },
        "2019-04": {
            "validhits": [
                {
                    "robot_agent": "Go-http-client/1.1",
                    "useragent": "Go-http-client/1.1",
                    "value": "3"
                }
            ]
        },
        "2019-05": {
            "validhits": [
                {
                    "robot_agent": "Go-http-client/1.1",
                    "useragent": "Go-http-client/1.1",
                    "value": "3"
                }
            ]
        },
        "2019-06": {
            "validhits": [
                {
                    "robot_agent": "Go-http-client/1.1",
                    "useragent": "Go-http-client/1.1",
                    "value": "3"
                }
            ]
        },
        "2019-07": {
            "validhits": [
                {
                    "robot_agent": "Go-http-client/1.1",
                    "useragent": "Go-http-client/1.1",
                    "value": "3"
                }
            ]
        },
        "2019-08": {
            "validhits": [
                {
                    "robot_agent": "Go-http-client/1.1",
                    "useragent": "Go-http-client/1.1",
                    "value": "3"
                }
            ]
        },
        "2019-09": {
            "validhits": [
                {
                    "robot_agent": "Go-http-client/1.1",
                    "useragent": "Go-http-client/1.1",
                    "value": "3"
                }
            ]
        },
        "2019-10": {
            "validhits": [
                {
                    "robot_agent": "Go-http-client/1.1",
                    "useragent": "Go-http-client/1.1",
                    "value": "3"
                }
            ]
        },
        "2019-11-01": {
            "validhits": [
                {
                    "robot_agent": "Go-http-client/1.1",
                    "useragent": "Go-http-client/1.1",
                    "value": "10"
                }
            ]
        },
        "2019-11-02": {
            "validhits": [
                {
                    "robot_agent": "Go-http-client/1.1",
                    "useragent": "Go-http-client/1.1",
                    "value": "10"
                }
            ]
        },
        "2019-11-03": {
            "validhits": [
                {
                    "robot_agent": "Go-http-client/1.1",
                    "useragent": "Go-http-client/1.1",
                    "value": "10"
                }
            ]
        },
        "2019-11-04": {
            "validhits": [
                {
                    "robot_agent": "Go-http-client/1.1",
                    "useragent": "Go-http-client/1.1",
                    "value": "10"
                }
            ]
        },
        "2019-11-05": {
            "validhits": [
                {
                    "robot_agent": "Go-http-client/1.1",
                    "useragent": "Go-http-client/1.1",
                    "value": "10"
                }
            ]
        },
        "2019-11-06": {
            "validhits": [
                {
                    "robot_agent": "Go-http-client/1.1",
                    "useragent": "Go-http-client/1.1",
                    "value": "110"
                }
            ]
        },
        "2019-11-07": {
            "validhits": [
                {
                    "robot_agent": "Go-http-client/1.1",
                    "useragent": "Go-http-client/1.1",
                    "value": "110"
                }
            ]
        }
    }
}